odoo8_addon_project_analytic_line_view-8.0.1.0.0.99.dev15-py2.7-nspkg.pth
odoo8_addon_project_analytic_line_view-8.0.1.0.0.99.dev15.dist-info/METADATA
odoo8_addon_project_analytic_line_view-8.0.1.0.0.99.dev15.dist-info/RECORD
odoo8_addon_project_analytic_line_view-8.0.1.0.0.99.dev15.dist-info/WHEEL
odoo8_addon_project_analytic_line_view-8.0.1.0.0.99.dev15.dist-info/namespace_packages.txt
odoo8_addon_project_analytic_line_view-8.0.1.0.0.99.dev15.dist-info/top_level.txt
odoo_addons/project_analytic_line_view/README.rst
odoo_addons/project_analytic_line_view/__init__.py
odoo_addons/project_analytic_line_view/__openerp__.py
odoo_addons/project_analytic_line_view/analytic_account.py
odoo_addons/project_analytic_line_view/analytic_account_view.xml
odoo_addons/project_analytic_line_view/i18n/ca.po
odoo_addons/project_analytic_line_view/i18n/de.po
odoo_addons/project_analytic_line_view/i18n/el_GR.po
odoo_addons/project_analytic_line_view/i18n/es.po
odoo_addons/project_analytic_line_view/i18n/es_MX.po
odoo_addons/project_analytic_line_view/i18n/fi.po
odoo_addons/project_analytic_line_view/i18n/fr.po
odoo_addons/project_analytic_line_view/i18n/hr.po
odoo_addons/project_analytic_line_view/i18n/project_analytic_line_view.pot
odoo_addons/project_analytic_line_view/i18n/pt.po
odoo_addons/project_analytic_line_view/i18n/pt_BR.po
odoo_addons/project_analytic_line_view/i18n/pt_PT.po
odoo_addons/project_analytic_line_view/i18n/sk_SK.po
odoo_addons/project_analytic_line_view/i18n/sl.po
odoo_addons/project_analytic_line_view/i18n/zh_CN.po
odoo_addons/project_analytic_line_view/static/description/icon.png
